.gitignore
.travis.yml
README.md
generate.sh
requirements.txt
setup.py
test_simple.py
korhal/__init__.py
korhal/hannanum.py
korhal/komoran.py
korhal/openkoreantext.py
korhal.egg-info/PKG-INFO
korhal.egg-info/SOURCES.txt
korhal.egg-info/dependency_links.txt
korhal.egg-info/requires.txt
korhal.egg-info/top_level.txt
korhal/aio/hannanum.py
korhal/aio/komoran.py
korhal/aio/openkoreantext.py
korhal/util/__init__.py
korhal/util/client.py
korhal/util/java.py
korhal/util/korhal_pb2.py
korhal/util/korhal_pb2_grpc.py