Metadata-Version: 2.1
Name: korhal
Version: 0.1.2
Summary: KOrean Rpc-based Application for Handy Application for Language-processing
Home-page: https://github.com/cookieshake/korhal
Author: cookieshake
Author-email: cookieshake.dev@gmail.com
License: UNKNOWN
Keywords: korean analysis tagger tokenizer
Platform: UNKNOWN
Requires-Python: >=2.6, !=3.0.*, !=3.1.*, !=3.2.*, !=3.3.*, !=3.4.*
